.gitignore
README.md
publish.sh
setup.py
src/.gitignore
src/__init__.py
src/bellande_motion_probability/__init__.py
src/bellande_motion_probability/bellande_motion_probability_api.py
src/bellande_motion_probability.egg-info/PKG-INFO
src/bellande_motion_probability.egg-info/SOURCES.txt
src/bellande_motion_probability.egg-info/dependency_links.txt
src/bellande_motion_probability.egg-info/entry_points.txt
src/bellande_motion_probability.egg-info/requires.txt
src/bellande_motion_probability.egg-info/top_level.txt