Metadata-Version: 2.1
Name: bellande_motion_probability
Version: 0.1.0
Summary: The Bellande Motion Probability algorithm calculates particle movement probabilities using Bellande distributions for enhanced motion estimation
Author: RonaldsonBellande
Author-email: ronaldsonbellande@gmail.com
Project-URL: Home, https://github.com/Robotics-Sensors/bellande_motion_probability
Project-URL: Homepage, https://github.com/Robotics-Sensors/bellande_motion_probability
Project-URL: documentation, https://github.com/Robotics-Sensors/bellande_motion_probability
Project-URL: repository, https://github.com/Robotics-Sensors/bellande_motion_probability
Keywords: package,setuptools
Classifier: License :: OSI Approved :: GNU General Public License v3 (GPLv3)
Classifier: Programming Language :: Python
Requires-Python: >=3.0
Requires-Dist: numpy
Provides-Extra: dev
Requires-Dist: pytest; extra == "dev"
Requires-Dist: pytest-cov[all]; extra == "dev"
Requires-Dist: mypy; extra == "dev"
Requires-Dist: black; extra == "dev"
